biblocpal/__init__.py
biblocpal/core.py
biblocpal/data.py
biblocpal/reasoning.py
biblocpal-0.1.0b0.dist-info/licenses/LICENSE
biblocpal-0.1.0b0.dist-info/METADATA
biblocpal-0.1.0b0.dist-info/WHEEL
biblocpal-0.1.0b0.dist-info/top_level.txt
biblocpal-0.1.0b0.dist-info/RECORD
