Metadata-Version: 2.4
Name: biblocpal
Version: 0.1.0b0
Summary: Biblocpal - Biblioteca de vocabulario, significados y razonamiento básico para IA.
Home-page: https://pypi.org/project/biblocpal/
Author: Tu Nombre
Author-email: tuemail@example.com
Classifier: Development Status :: 4 - Beta
Classifier: Programming Language :: Python :: 3
Classifier: License :: OSI Approved :: MIT License
Classifier: Operating System :: OS Independent
Requires-Python: >=3.6
License-File: LICENSE
Dynamic: author
Dynamic: author-email
Dynamic: classifier
Dynamic: description
Dynamic: description-content-type
Dynamic: home-page
Dynamic: license-file
Dynamic: requires-python
Dynamic: summary
